Metadata-Version: 2.1
Name: pomerium-http-adapter
Version: 0.5
Summary: Transport adapter for requests to handle Pomerium authentication
Home-page: https://github.com/elastx/python-pomerium_http_adapter
Author: Joel Rangsmo
Author-email: joel.rangsmo@elastx.se
License: Apache License 2.0
Download-URL: https://github.com/elastx/python-pomerium_http_adapter/archive/v0.5.tar.gz
Keywords: pomerium,requests,adapter
Platform: UNKNOWN
Classifier: Development Status :: 3 - Alpha
Classifier: Intended Audience :: Developers
Classifier: License :: OSI Approved :: Apache Software License
Classifier: Programming Language :: Python :: 3.8
Classifier: Programming Language :: Python :: 3.9
Classifier: Programming Language :: Python :: 3.10
Classifier: Environment :: Plugins
Classifier: Topic :: Internet :: WWW/HTTP
License-File: LICENSE.txt
